<annotation verified="yes">
                                    <folder>Annotation</folder>
                                    <filename>IMG_20230309_174517_237</filename>
                                    <path>C:\tflow\JPEGImages\IMG_20230309_174517_237.jpg</path>
                                    <source>
                                        <database>Unknown</database>
                                    </source>
                                    <size>
                                        <width>3456</width>
                                        <height>3456</height>
                                        <depth>3</depth>
                                    </size>
                                    <segmented>0</segmented>
                                    <object>
                                            <name>broken_bottles</name>
                                            <pose>Unspecified</pose>
                                            <truncated>0</truncated>
                                            <difficult>0</difficult>
                                            <bndbox>
                                                <xmin>1605</xmin>
                                                <ymin>774</ymin>
                                                <xmax>2836</xmax>
                                                <ymax>1751</ymax>
                                            </bndbox>
                                    </object>
                                    </annotation>